primerD/__init__.py
primerD/core.py
primerD/gui.py
primerD/utils.py
primerd-0.1.1.dist-info/METADATA
primerd-0.1.1.dist-info/WHEEL
primerd-0.1.1.dist-info/top_level.txt
primerd-0.1.1.dist-info/RECORD
