Metadata-Version: 2.4
Name: primerD
Version: 0.1.1
Summary: A Python package for designing PCR primers
Home-page: https://github.com/sarahbiotech/primerD.git
Author: Sarah Ali
Author-email: alsayedsarah01@gmail.com
Classifier: Programming Language :: Python :: 3
Classifier: License :: OSI Approved :: MIT License
Classifier: Operating System :: OS Independent
Requires-Python: >=3.7
Dynamic: author
Dynamic: author-email
Dynamic: classifier
Dynamic: description
Dynamic: description-content-type
Dynamic: home-page
Dynamic: requires-python
Dynamic: summary
